digital/template/user/src/cordic_serial.v
`timescale 1ns / 1ps
//////////////////////////////////////////////////////////////////////////////////
// Company: 
// Engineer: 
// 
// Create Date: 2022/09/04 11:23:19
// Design Name: 
// Module Name: cordic_serial
// Project Name: 
// Target Devices: 
// Tool Versions: 
// Description: 
// 
// Dependencies: 
// 
// Revision:
// Revision 0.01 - File Created
// Additional Comments:
// 
//////////////////////////////////////////////////////////////////////////////////


module cordic_serial(
    input signed [31:0]    x,
    input signed [31:0]    y,
    input           clk,
    output reg [31:0]   phase
    );

    //FSM_parameter
    localparam IDLE = 2'd0;
    localparam WORK = 2'd1;
    localparam DONE = 2'd2;

    reg     [1:0]state ;
    reg     [1:0]next_state;

    reg     [6:0]counter;

    wire   [31:0] rot[15:0];

//旋转角度查找表
assign  rot[0]  = 32'd2949120 ;     //45度*2^16
assign  rot[1]  = 32'd1740992 ;     //26.5651度*2^16
assign  rot[2]  = 32'd919872  ;     //14.0362度*2^16
assign  rot[3]  = 32'd466944  ;     //7.1250度*2^16
assign  rot[4]  = 32'd234368  ;     //3.5763度*2^16
assign  rot[5]  = 32'd117312  ;     //1.7899度*2^16
assign  rot[6]  = 32'd58688   ;     //0.8952度*2^16
assign  rot[7]  = 32'd29312   ;     //0.4476度*2^16
assign  rot[8]  = 32'd14656   ;     //0.2238度*2^16
assign  rot[9]  = 32'd7360    ;     //0.1119度*2^16
assign  rot[10] = 32'd3648    ;     //0.0560度*2^16
assign  rot[11] = 32'd1856    ;     //0.0280度*2^16
assign  rot[12] = 32'd896     ;     //0.0140度*2^16
assign  rot[13] = 32'd448     ;     //0.0070度*2^16
assign  rot[14] = 32'd256     ;     //0.0035度*2^16
assign  rot[15] = 32'd128     ;     //0.0018度*2^16

    always @(posedge clk) begin
        state<=next_state;
        case(state)
        IDLE:next_state<=WORK;
        WORK:next_state<= counter==14?DONE:WORK;
        DONE:next_state<=IDLE;

        default:next_state<=IDLE;
        endcase
    end

    reg signed [31:0] x_shift;
    reg signed [31:0] y_shift;
    reg signed [31:0] z_rot;

    wire     D_sign;
    assign   D_sign=~y_shift[31];

    always @(posedge clk ) begin
        case(state)
        IDLE:
        begin
            x_shift<=x;
            y_shift<=y;
            z_rot<=0;
        end

        WORK:if(D_sign)
        begin
            x_shift       <= x_shift + (y_shift>>>counter);
            y_shift       <= y_shift - (x_shift>>>counter);
            z_rot         <= z_rot  + rot[counter];
        end
        else begin
            x_shift       <= x_shift - (y_shift>>>counter);
            y_shift       <= y_shift + (x_shift>>>counter);
            z_rot         <= z_rot  - rot[counter];
        end

        DONE:
        begin
            phase<=z_rot;
        end
        default : ;
        endcase
    end

    always @(posedge clk ) begin
        if(state==IDLE && next_state==WORK)
            counter<=0;
        else if(state==WORK)begin
        if(counter<4'd14)
            counter<=counter+1;
            else
            counter<=counter;
        end
        else
            counter<=0;
    end



endmodule

digital/template/user/sim/tb_cordic_serial.v
`timescale 1ns / 1ps
// 生成 VCD 波形文件（适用于 GTKWave）
   
module tb_cordic_serial;
    // 定义输入信号
    reg signed [31:0] x;
    reg signed [31:0] y;
    reg clk;

    // 定义输出信号
    wire [31:0] phase;

   
    // 实例化被测模块（DUT）
    cordic_serial uut (
        .x(x),
        .y(y),
        .clk(clk),
        .phase(phase)
    );

    // 生成 10ns 时钟（100MHz）
    always #5 clk = ~clk;

    // 测试过程
    initial begin
        // 初始化信号
        clk = 0;
        x = 0;
        y = 0;

        // 开始测试
        $display("Starting CORDIC Test...");

        // 测试向量 1: 45 度 (x=y)
        #10;
        x = 32'd1000000;
        y = 32'd1000000;
        $display("Test 1: X = %d, Y = %d", x, y);

        // 测试向量 2: 0 度 (y=0)
        #300;
        x = 32'd1000000;
        y = 32'd0;
        $display("Test 2: X = %d, Y = %d", x, y);

        // 测试向量 3: -45 度 (x=-y)
        #300;
        x = 32'd1000000;
        y = -32'd1000000;
        $display("Test 3: X = %d, Y = %d", x, y);

        // 测试向量 4: 90 度 (x=0)
        #300;
        x = 32'd0;
        y = 32'd1000000;
        $display("Test 4: X = %d, Y = %d", x, y);

        // 测试向量 5: -90 度 (x=0, y<0)
        #300;
        x = 32'd0;
        y = -32'd1000000;
        $display("Test 5: X = %d, Y = %d", x, y);

        // 等待计算完成
        #500;
        $display("CORDIC Calculation Finished!");
        $display("Final Output Phase: %d", phase);

    end

     initial begin
        $dumpfile("waveform/cordic_serial_tb.vcd");
        $dumpvars(0, tb_cordic_serial);
        // 结束仿真
        #50000 $finish;
    end


endmodule

digital/template/waveform/cordic_serial_tb.vcd
$date
	Tue Mar 18 14:09:08 2025
$end
$version
	Icarus Verilog
$end
$timescale
	1ps
$end
$scope module tb_cordic_serial $end
$var wire 32 ! phase [31:0] $end
$var reg 1 " clk $end
$var reg 32 # x [31:0] $end
$var reg 32 $ y [31:0] $end
$scope module uut $end
$var wire 1 % D_sign $end
$var wire 1 " clk $end
$var wire 32 & x [31:0] $end
$var wire 32 ' y [31:0] $end
$var parameter 2 ( DONE $end
$var parameter 2 ) IDLE $end
$var parameter 2 * WORK $end
$var reg 7 + counter [6:0] $end
$var reg 2 , next_state [1:0] $end
$var reg 32 - phase [31:0] $end
$var reg 2 . state [1:0] $end
$var reg 32 / x_shift [31:0] $end
$var reg 32 0 y_shift [31:0] $end
$var reg 32 1 z_rot [31:0] $end
$upscope $end
$upscope $end
$enddefinitions $end
$comment Show the parameter values. $end
$dumpall
b1 *
b0 )
b10 (
$end
#0
$dumpvars
bx 1
bx 0
bx /
bx .
bx -
bx ,
bx +
b0 '
b0 &
x%
b0 $
b0 #
0"
bx !
$end
#5000
b0 ,
b0 +
1"
#10000
0"
b11110100001001000000 $
b11110100001001000000 '
b11110100001001000000 #
b11110100001001000000 &
#15000
b0 .
1"
#20000
0"
#25000
1%
b1 ,
b0 1
b11110100001001000000 0
b11110100001001000000 /
1"
#30000
0"
#35000
b1 .
1"
#40000
0"
#45000
b1011010000000000000000 1
b0 0
b111101000010010000000 /
b1 +
1"
#50000
0"
#55000
0%
b10 +
b10001111001000011000000 1
b11111111111100001011110111000000 0
1"
#60000
0"
#65000
b1110011000011110000000 1
b11111111111110000101111011100000 0
b1000100101010100010000 /
b11 +
1"
#70000
0"
#75000
b100 +
b1100100110011110000000 1
b11111111111111001010100110000010 0
b1000110100100100110100 /
1"
#80000
0"
#85000
b1011101101010000000000 1
b11111111111111101101111000010101 0
b1000110111111010011100 /
b101 +
1"
#90000
0"
#95000
b110 +
b1011010000100111000000 1
b11111111111111111111101000001001 0
b1000111000011110101100 /
1"
#100000
0"
#105000
1%
b1011000010010010000000 1
b1000100000100111 0
b1000111000011111000100 /
b111 +
1"
#110000
0"
#115000
b1000 +
b1011001001011100000000 1
b100000100011000 0
b1000111000100011010100 /
1"
#120000
0"
#125000
b1011001101000001000000 1
b1110110010000 0
b1000111000100100010101 /
b1001 +
1"
#130000
0"
#135000
b1010 +
b1011001110110100000000 1
b101111001100 0
b1000111000100100100011 /
1"
#140000
0"
#145000
b1011001111101101000000 1
b1011101010 0
b1000111000100100100101 /
b1011 +
1"
#150000
0"
#155000
0%
b1100 +
b1011010000001010000000 1
b11111111111111111111111001111001 0
1"
#160000
0"
#165000
1%
b1011001111111100000000 1
b10110001 0
b1000111000100100100110 /
b1101 +
1"
#170000
0"
#175000
0%
b1110 +
b1011010000000011000000 1
b11111111111111111111111110010101 0
1"
#180000
0"
#185000
1%
b10 ,
b1011001111111111000000 1
b100011 0
b1000111000100100100111 /
1"
#190000
0"
#195000
0%
b1011010000000011000000 1
b11111111111111111111111110010101 0
b10 .
1"
#200000
0"
#205000
b0 ,
b1011010000000011000000 !
b1011010000000011000000 -
b0 +
1"
#210000
0"
#215000
b0 .
1"
#220000
0"
#225000
1%
b1 ,
b0 1
b11110100001001000000 0
b11110100001001000000 /
1"
#230000
0"
#235000
b1 .
1"
#240000
0"
#245000
b1011010000000000000000 1
b0 0
b111101000010010000000 /
b1 +
1"
#250000
0"
#255000
0%
b10 +
b10001111001000011000000 1
b11111111111100001011110111000000 0
1"
#260000
0"
#265000
b1110011000011110000000 1
b11111111111110000101111011100000 0
b1000100101010100010000 /
b11 +
1"
#270000
0"
#275000
b100 +
b1100100110011110000000 1
b11111111111111001010100110000010 0
b1000110100100100110100 /
1"
#280000
0"
#285000
b1011101101010000000000 1
b11111111111111101101111000010101 0
b1000110111111010011100 /
b101 +
1"
#290000
0"
#295000
b110 +
b1011010000100111000000 1
b11111111111111111111101000001001 0
b1000111000011110101100 /
1"
#300000
0"
#305000
1%
b1011000010010010000000 1
b1000100000100111 0
b1000111000011111000100 /
b111 +
1"
#310000
0"
b0 $
b0 '
#315000
b1000 +
b1011001001011100000000 1
b100000100011000 0
b1000111000100011010100 /
1"
#320000
0"
#325000
b1011001101000001000000 1
b1110110010000 0
b1000111000100100010101 /
b1001 +
1"
#330000
0"
#335000
b1010 +
b1011001110110100000000 1
b101111001100 0
b1000111000100100100011 /
1"
#340000
0"
#345000
b1011001111101101000000 1
b1011101010 0
b1000111000100100100101 /
b1011 +
1"
#350000
0"
#355000
0%
b1100 +
b1011010000001010000000 1
b11111111111111111111111001111001 0
1"
#360000
0"
#365000
1%
b1011001111111100000000 1
b10110001 0
b1000111000100100100110 /
b1101 +
1"
#370000
0"
#375000
0%
b1110 +
b1011010000000011000000 1
b11111111111111111111111110010101 0
1"
#380000
0"
#385000
1%
b10 ,
b1011001111111111000000 1
b100011 0
b1000111000100100100111 /
1"
#390000
0"
#395000
0%
b1011010000000011000000 1
b11111111111111111111111110010101 0
b10 .
1"
#400000
0"
#405000
b0 ,
b0 +
1"
#410000
0"
#415000
b0 .
1"
#420000
0"
#425000
1%
b1 ,
b0 1
b0 0
b11110100001001000000 /
1"
#430000
0"
#435000
b1 .
1"
#440000
0"
#445000
0%
b1011010000000000000000 1
b11111111111100001011110111000000 0
b1 +
1"
#450000
0"
#455000
b10 +
b100100110111101000000 1
b11111111111110000101111011100000 0
b101101110001101100000 /
1"
#460000
0"
#465000
b1000110011000000000 1
b11111111111111100001011110111000 0
b110001100101110101000 /
b11 +
1"
#470000
0"
#475000
1%
b100 +
b11111111111111010100011000000000 1
b10011000100101101 0
b110010000100010110001 /
1"
#480000
0"
#485000
0%
b1101100110000000 1
b11111111111111111010000010100010 0
b110010001101111000011 /
b101 +
1"
#490000
0"
#495000
1%
b110 +
b11111111111111110000111101000000 1
b110100110000000 0
b110010001111010111110 /
1"
#500000
0"
#505000
b11111111111111111111010010000000 1
b10100000110 0
b110010010000001100100 /
b111 +
1"
#510000
0"
#515000
0%
b1000 +
b110011100000000 1
b11111111111111111101001011000110 0
b110010010000001101110 /
1"
#520000
0"
#525000
b10110111000000 1
b11111111111111111110101111100110 0
b110010010000010011100 /
b1001 +
1"
#530000
0"
#535000
b1010 +
b1000100000000 1
b11111111111111111111100001110110 0
b110010010000010100111 /
1"
#540000
0"
#545000
b1011000000 1
b11111111111111111111111010111110 0
b110010010000010101001 /
b1011 +
1"
#550000
0"
#555000
1%
b1100 +
b11111111111111111111101110000000 1
b111100010 0
b110010010000010101010 /
1"
#560000
0"
#565000
b11111111111111111111111100000000 1
b1010000 0
b1101 +
1"
#570000
0"
#575000
0%
b1110 +
b11000000 1
b11111111111111111111111110000111 0
1"
#580000
0"
#585000
b10 ,
b11111111111111111111111111000000 1
b11111111111111111111111111101011 0
b110010010000010101011 /
1"
#590000
0"
#595000
1%
b11111111111111111111111011000000 1
b1001111 0
b110010010000010101100 /
b10 .
1"
#600000
0"
#605000
b0 ,
b11111111111111111111111011000000 !
b11111111111111111111111011000000 -
b0 +
1"
#610000
0"
b11111111111100001011110111000000 $
b11111111111100001011110111000000 '
#615000
b0 .
1"
#620000
0"
#625000
0%
b1 ,
b0 1
b11111111111100001011110111000000 0
b11110100001001000000 /
1"
#630000
0"
#635000
b1 .
1"
#640000
0"
#645000
1%
b11111111110100110000000000000000 1
b0 0
b111101000010010000000 /
b1 +
1"
#650000
0"
#655000
0%
b10 +
b11111111111011011001000011000000 1
b11111111111100001011110111000000 0
1"
#660000
0"
#665000
b11111111110111111000011110000000 1
b11111111111110000101111011100000 0
b1000100101010100010000 /
b11 +
1"
#670000
0"
#675000
b100 +
b11111111110110000110011110000000 1
b11111111111111001010100110000010 0
b1000110100100100110100 /
1"
#680000
0"
#685000
b11111111110101001101010000000000 1
b11111111111111101101111000010101 0
b1000110111111010011100 /
b101 +
1"
#690000
0"
#695000
b110 +
b11111111110100110000100111000000 1
b11111111111111111111101000001001 0
b1000111000011110101100 /
1"
#700000
0"
#705000
1%
b11111111110100100010010010000000 1
b1000100000100111 0
b1000111000011111000100 /
b111 +
1"
#710000
0"
#715000
b1000 +
b11111111110100101001011100000000 1
b100000100011000 0
b1000111000100011010100 /
1"
#720000
0"
#725000
b11111111110100101101000001000000 1
b1110110010000 0
b1000111000100100010101 /
b1001 +
1"
#730000
0"
#735000
b1010 +
b11111111110100101110110100000000 1
b101111001100 0
b1000111000100100100011 /
1"
#740000
0"
#745000
b11111111110100101111101101000000 1
b1011101010 0
b1000111000100100100101 /
b1011 +
1"
#750000
0"
#755000
0%
b1100 +
b11111111110100110000001010000000 1
b11111111111111111111111001111001 0
1"
#760000
0"
#765000
1%
b11111111110100101111111100000000 1
b10110001 0
b1000111000100100100110 /
b1101 +
1"
#770000
0"
#775000
0%
b1110 +
b11111111110100110000000011000000 1
b11111111111111111111111110010101 0
1"
#780000
0"
#785000
1%
b10 ,
b11111111110100101111111111000000 1
b100011 0
b1000111000100100100111 /
1"
#790000
0"
#795000
0%
b11111111110100110000000011000000 1
b11111111111111111111111110010101 0
b10 .
1"
#800000
0"
#805000
b0 ,
b11111111110100110000000011000000 !
b11111111110100110000000011000000 -
b0 +
1"
#810000
0"
#815000
b0 .
1"
#820000
0"
#825000
b1 ,
b0 1
b11111111111100001011110111000000 0
b11110100001001000000 /
1"
#830000
0"
#835000
b1 .
1"
#840000
0"
#845000
1%
b11111111110100110000000000000000 1
b0 0
b111101000010010000000 /
b1 +
1"
#850000
0"
#855000
0%
b10 +
b11111111111011011001000011000000 1
b11111111111100001011110111000000 0
1"
#860000
0"
#865000
b11111111110111111000011110000000 1
b11111111111110000101111011100000 0
b1000100101010100010000 /
b11 +
1"
#870000
0"
#875000
b100 +
b11111111110110000110011110000000 1
b11111111111111001010100110000010 0
b1000110100100100110100 /
1"
#880000
0"
#885000
b11111111110101001101010000000000 1
b11111111111111101101111000010101 0
b1000110111111010011100 /
b101 +
1"
#890000
0"
#895000
b110 +
b11111111110100110000100111000000 1
b11111111111111111111101000001001 0
b1000111000011110101100 /
1"
#900000
0"
#905000
1%
b11111111110100100010010010000000 1
b1000100000100111 0
b1000111000011111000100 /
b111 +
1"
#910000
0"
b11110100001001000000 $
b11110100001001000000 '
b0 #
b0 &
#915000
b1000 +
b11111111110100101001011100000000 1
b100000100011000 0
b1000111000100011010100 /
1"
#920000
0"
#925000
b11111111110100101101000001000000 1
b1110110010000 0
b1000111000100100010101 /
b1001 +
1"
#930000
0"
#935000
b1010 +
b11111111110100101110110100000000 1
b101111001100 0
b1000111000100100100011 /
1"
#940000
0"
#945000
b11111111110100101111101101000000 1
b1011101010 0
b1000111000100100100101 /
b1011 +
1"
#950000
0"
#955000
0%
b1100 +
b11111111110100110000001010000000 1
b11111111111111111111111001111001 0
1"
#960000
0"
#965000
1%
b11111111110100101111111100000000 1
b10110001 0
b1000111000100100100110 /
b1101 +
1"
#970000
0"
#975000
0%
b1110 +
b11111111110100110000000011000000 1
b11111111111111111111111110010101 0
1"
#980000
0"
#985000
1%
b10 ,
b11111111110100101111111111000000 1
b100011 0
b1000111000100100100111 /
1"
#990000
0"
#995000
0%
b11111111110100110000000011000000 1
b11111111111111111111111110010101 0
b10 .
1"
#1000000
0"
#1005000
b0 ,
b0 +
1"
#1010000
0"
#1015000
b0 .
1"
#1020000
0"
#1025000
1%
b1 ,
b0 1
b11110100001001000000 0
b0 /
1"
#1030000
0"
#1035000
b1 .
1"
#1040000
0"
#1045000
b1011010000000000000000 1
b11110100001001000000 /
b1 +
1"
#1050000
0"
#1055000
b10 +
b10001111001000011000000 1
b1111010000100100000 0
b101101110001101100000 /
1"
#1060000
0"
#1065000
b10101011001101000000000 1
b11110100001001000 0
b110001100101110101000 /
b11 +
1"
#1070000
0"
#1075000
0%
b100 +
b10111001011101000000000 1
b11111111111111101100111011010011 0
b110010000100010110001 /
1"
#1080000
0"
#1085000
1%
b10110010010011010000000 1
b101111101011110 0
b110010001101111000100 /
b101 +
1"
#1090000
0"
#1095000
0%
b110 +
b10110101111000011000000 1
b11111111111111111001011010000000 0
b110010001111010111110 /
1"
#1100000
0"
#1105000
b10110100000101110000000 1
b11111111111111111111101011111010 0
b110010010000001100100 /
b111 +
1"
#1110000
0"
#1115000
1%
b1000 +
b10110011001100100000000 1
b10110100111010 0
b110010010000001101111 /
1"
#1120000
0"
#1125000
b10110011101001001000000 1
b1010000011010 0
b110010010000010011100 /
b1001 +
1"
#1130000
0"
#1135000
b1010 +
b10110011110111100000000 1
b11110001010 0
b110010010000010100110 /
1"
#1140000
0"
#1145000
b10110011111110101000000 1
b101000010 0
b110010010000010100111 /
b1011 +
1"
#1150000
0"
#1155000
0%
b1100 +
b10110100000010010000000 1
b11111111111111111111111000011110 0
1"
#1160000
0"
#1165000
b10110100000000100000000 1
b11111111111111111111111110110000 0
b110010010000010101000 /
b1101 +
1"
#1170000
0"
#1175000
1%
b1110 +
b10110011111111101000000 1
b1111001 0
b110010010000010101001 /
1"
#1180000
0"
#1185000
b10 ,
b10110100000000001000000 1
b10101 0
1"
#1190000
0"
#1195000
0%
b10110100000000101000000 1
b11111111111111111111111110110001 0
b10 .
1"
#1200000
0"
#1205000
b0 ,
b10110100000000101000000 !
b10110100000000101000000 -
b0 +
1"
#1210000
0"
b11111111111100001011110111000000 $
b11111111111100001011110111000000 '
#1215000
b0 .
1"
#1220000
0"
#1225000
b1 ,
b0 1
b11111111111100001011110111000000 0
b0 /
1"
#1230000
0"
#1235000
b1 .
1"
#1240000
0"
#1245000
b11111111110100110000000000000000 1
b11110100001001000000 /
b1 +
1"
#1250000
0"
#1255000
b10 +
b11111111101110000110111101000000 1
b11111111111110000101111011100000 0
b101101110001101100000 /
1"
#1260000
0"
#1265000
b11111111101010100110011000000000 1
b11111111111111100001011110111000 0
b110001100101110101000 /
b11 +
1"
#1270000
0"
#1275000
1%
b100 +
b11111111101000110100011000000000 1
b10011000100101101 0
b110010000100010110001 /
1"
#1280000
0"
#1285000
0%
b11111111101001101101100110000000 1
b11111111111111111010000010100010 0
b110010001101111000011 /
b101 +
1"
#1290000
0"
#1295000
1%
b110 +
b11111111101001010000111101000000 1
b110100110000000 0
b110010001111010111110 /
1"
#1300000
0"
#1305000
b11111111101001011111010010000000 1
b10100000110 0
b110010010000001100100 /
b111 +
1"
#1310000
0"
#1315000
0%
b1000 +
b11111111101001100110011100000000 1
b11111111111111111101001011000110 0
b110010010000001101110 /
1"
#1320000
0"
#1325000
b11111111101001100010110111000000 1
b11111111111111111110101111100110 0
b110010010000010011100 /
b1001 +
1"
#1330000
0"
#1335000
b1010 +
b11111111101001100001000100000000 1
b11111111111111111111100001110110 0
b110010010000010100111 /
1"
#1340000
0"
#1345000
b11111111101001100000001011000000 1
b11111111111111111111111010111110 0
b110010010000010101001 /
b1011 +
1"
#1350000
0"
#1355000
1%
b1100 +
b11111111101001011111101110000000 1
b111100010 0
b110010010000010101010 /
1"
#1360000
0"
#1365000
b11111111101001011111111100000000 1
b1010000 0
b1101 +
1"
#1370000
0"
#1375000
0%
b1110 +
b11111111101001100000000011000000 1
b11111111111111111111111110000111 0
1"
#1380000
0"
#1385000
b10 ,
b11111111101001011111111111000000 1
b11111111111111111111111111101011 0
b110010010000010101011 /
1"
#1390000
0"
#1395000
1%
b11111111101001011111111011000000 1
b1001111 0
b110010010000010101100 /
b10 .
1"
#1400000
0"
#1405000
b0 ,
b11111111101001011111111011000000 !
b11111111101001011111111011000000 -
b0 +
1"
#1410000
0"
#1415000
b0 .
1"
#1420000
0"
#1425000
0%
b1 ,
b0 1
b11111111111100001011110111000000 0
b0 /
1"
#1430000
0"
#1435000
b1 .
1"
#1440000
0"
#1445000
b11111111110100110000000000000000 1
b11110100001001000000 /
b1 +
1"
#1450000
0"
#1455000
b10 +
b11111111101110000110111101000000 1
b11111111111110000101111011100000 0
b101101110001101100000 /
1"
#1460000
0"
#1465000
b11111111101010100110011000000000 1
b11111111111111100001011110111000 0
b110001100101110101000 /
b11 +
1"
#1470000
0"
#1475000
1%
b100 +
b11111111101000110100011000000000 1
b10011000100101101 0
b110010000100010110001 /
1"
#1480000
0"
#1485000
0%
b11111111101001101101100110000000 1
b11111111111111111010000010100010 0
b110010001101111000011 /
b101 +
1"
#1490000
0"
#1495000
1%
b110 +
b11111111101001010000111101000000 1
b110100110000000 0
b110010001111010111110 /
1"
#1500000
0"
#1505000
b11111111101001011111010010000000 1
b10100000110 0
b110010010000001100100 /
b111 +
1"
#1510000
0"
#1515000
0%
b1000 +
b11111111101001100110011100000000 1
b11111111111111111101001011000110 0
b110010010000001101110 /
1"
#1520000
0"
#1525000
b11111111101001100010110111000000 1
b11111111111111111110101111100110 0
b110010010000010011100 /
b1001 +
1"
#1530000
0"
#1535000
b1010 +
b11111111101001100001000100000000 1
b11111111111111111111100001110110 0
b110010010000010100111 /
1"
#1540000
0"
#1545000
b11111111101001100000001011000000 1
b11111111111111111111111010111110 0
b110010010000010101001 /
b1011 +
1"
#1550000
0"
#1555000
1%
b1100 +
b11111111101001011111101110000000 1
b111100010 0
b110010010000010101010 /
1"
#1560000
0"
#1565000
b11111111101001011111111100000000 1
b1010000 0
b1101 +
1"
#1570000
0"
#1575000
0%
b1110 +
b11111111101001100000000011000000 1
b11111111111111111111111110000111 0
1"
#1580000
0"
#1585000
b10 ,
b11111111101001011111111111000000 1
b11111111111111111111111111101011 0
b110010010000010101011 /
1"
#1590000
0"
#1595000
1%
b11111111101001011111111011000000 1
b1001111 0
b110010010000010101100 /
b10 .
1"
#1600000
0"
#1605000
b0 ,
b0 +
1"
#1610000
0"
#1615000
b0 .
1"
#1620000
0"
#1625000
0%
b1 ,
b0 1
b11111111111100001011110111000000 0
b0 /
1"
#1630000
0"
#1635000
b1 .
1"
#1640000
0"
#1645000
b11111111110100110000000000000000 1
b11110100001001000000 /
b1 +
1"
#1650000
0"
#1655000
b10 +
b11111111101110000110111101000000 1
b11111111111110000101111011100000 0
b101101110001101100000 /
1"
#1660000
0"
#1665000
b11111111101010100110011000000000 1
b11111111111111100001011110111000 0
b110001100101110101000 /
b11 +
1"
#1670000
0"
#1675000
1%
b100 +
b11111111101000110100011000000000 1
b10011000100101101 0
b110010000100010110001 /
1"
#1680000
0"
#1685000
0%
b11111111101001101101100110000000 1
b11111111111111111010000010100010 0
b110010001101111000011 /
b101 +
1"
#1690000
0"
#1695000
1%
b110 +
b11111111101001010000111101000000 1
b110100110000000 0
b110010001111010111110 /
1"
#1700000
0"
#1705000
b11111111101001011111010010000000 1
b10100000110 0
b110010010000001100100 /
b111 +
1"
#1710000
0"
#1715000
0%
b1000 +
b11111111101001100110011100000000 1
b11111111111111111101001011000110 0
b110010010000001101110 /
1"
#1720000
0"
#1725000
b11111111101001100010110111000000 1
b11111111111111111110101111100110 0
b110010010000010011100 /
b1001 +
1"
#1730000
0"
#1735000
b1010 +
b11111111101001100001000100000000 1
b11111111111111111111100001110110 0
b110010010000010100111 /
1"
#1740000
0"
#1745000
b11111111101001100000001011000000 1
b11111111111111111111111010111110 0
b110010010000010101001 /
b1011 +
1"
#1750000
0"
#1755000
1%
b1100 +
b11111111101001011111101110000000 1
b111100010 0
b110010010000010101010 /
1"
#1760000
0"
#1765000
b11111111101001011111111100000000 1
b1010000 0
b1101 +
1"
#1770000
0"
#1775000
0%
b1110 +
b11111111101001100000000011000000 1
b11111111111111111111111110000111 0
1"
#1780000
0"
#1785000
b10 ,
b11111111101001011111111111000000 1
b11111111111111111111111111101011 0
b110010010000010101011 /
1"
#1790000
0"
#1795000
1%
b11111111101001011111111011000000 1
b1001111 0
b110010010000010101100 /
b10 .
1"
#1800000
0"
#1805000
b0 ,
b0 +
1"
#1810000
0"
#1815000
b0 .
1"
#1820000
0"
#1825000
0%
b1 ,
b0 1
b11111111111100001011110111000000 0
b0 /
1"
#1830000
0"
#1835000
b1 .
1"
#1840000
0"
#1845000
b11111111110100110000000000000000 1
b11110100001001000000 /
b1 +
1"
#1850000
0"
#1855000
b10 +
b11111111101110000110111101000000 1
b11111111111110000101111011100000 0
b101101110001101100000 /
1"
#1860000
0"
#1865000
b11111111101010100110011000000000 1
b11111111111111100001011110111000 0
b110001100101110101000 /
b11 +
1"
#1870000
0"
#1875000
1%
b100 +
b11111111101000110100011000000000 1
b10011000100101101 0
b110010000100010110001 /
1"
#1880000
0"
#1885000
0%
b11111111101001101101100110000000 1
b11111111111111111010000010100010 0
b110010001101111000011 /
b101 +
1"
#1890000
0"
#1895000
1%
b110 +
b11111111101001010000111101000000 1
b110100110000000 0
b110010001111010111110 /
1"
#1900000
0"
#1905000
b11111111101001011111010010000000 1
b10100000110 0
b110010010000001100100 /
b111 +
1"
#1910000
0"
#1915000
0%
b1000 +
b11111111101001100110011100000000 1
b11111111111111111101001011000110 0
b110010010000001101110 /
1"
#1920000
0"
#1925000
b11111111101001100010110111000000 1
b11111111111111111110101111100110 0
b110010010000010011100 /
b1001 +
1"
#1930000
0"
#1935000
b1010 +
b11111111101001100001000100000000 1
b11111111111111111111100001110110 0
b110010010000010100111 /
1"
#1940000
0"
#1945000
b11111111101001100000001011000000 1
b11111111111111111111111010111110 0
b110010010000010101001 /
b1011 +
1"
#1950000
0"
#1955000
1%
b1100 +
b11111111101001011111101110000000 1
b111100010 0
b110010010000010101010 /
1"
#1960000
0"
#1965000
b11111111101001011111111100000000 1
b1010000 0
b1101 +
1"
#1970000
0"
#1975000
0%
b1110 +
b11111111101001100000000011000000 1
b11111111111111111111111110000111 0
1"
#1980000
0"
#1985000
b10 ,
b11111111101001011111111111000000 1
b11111111111111111111111111101011 0
b110010010000010101011 /
1"
#1990000
0"
#1995000
1%
b11111111101001011111111011000000 1
b1001111 0
b110010010000010101100 /
b10 .
1"
#2000000
0"
#2005000
b0 ,
b0 +
1"
#2010000
0"
#2015000
b0 .
1"
#2020000
0"
#2025000
0%
b1 ,
b0 1
b11111111111100001011110111000000 0
b0 /
1"
#2030000
0"
#2035000
b1 .
1"
#2040000
0"
#2045000
b11111111110100110000000000000000 1
b11110100001001000000 /
b1 +
1"
#2050000
0"
#2055000
b10 +
b11111111101110000110111101000000 1
b11111111111110000101111011100000 0
b101101110001101100000 /
1"
#2060000
0"
#2065000
b11111111101010100110011000000000 1
b11111111111111100001011110111000 0
b110001100101110101000 /
b11 +
1"
#2070000
0"
#2075000
1%
b100 +
b11111111101000110100011000000000 1
b10011000100101101 0
b110010000100010110001 /
1"
#2080000
0"
#2085000
0%
b11111111101001101101100110000000 1
b11111111111111111010000010100010 0
b110010001101111000011 /
b101 +
1"
#2090000
0"
#2095000
1%
b110 +
b11111111101001010000111101000000 1
b110100110000000 0
b110010001111010111110 /
1"
#2100000
0"
#2105000
b11111111101001011111010010000000 1
b10100000110 0
b110010010000001100100 /
b111 +
1"
#2110000
0"
#2115000
0%
b1000 +
b11111111101001100110011100000000 1
b11111111111111111101001011000110 0
b110010010000001101110 /
1"
#2120000
0"
#2125000
b11111111101001100010110111000000 1
b11111111111111111110101111100110 0
b110010010000010011100 /
b1001 +
1"
#2130000
0"
#2135000
b1010 +
b11111111101001100001000100000000 1
b11111111111111111111100001110110 0
b110010010000010100111 /
1"
#2140000
0"
#2145000
b11111111101001100000001011000000 1
b11111111111111111111111010111110 0
b110010010000010101001 /
b1011 +
1"
#2150000
0"
#2155000
1%
b1100 +
b11111111101001011111101110000000 1
b111100010 0
b110010010000010101010 /
1"
#2160000
0"
#2165000
b11111111101001011111111100000000 1
b1010000 0
b1101 +
1"
#2170000
0"
#2175000
0%
b1110 +
b11111111101001100000000011000000 1
b11111111111111111111111110000111 0
1"
#2180000
0"
#2185000
b10 ,
b11111111101001011111111111000000 1
b11111111111111111111111111101011 0
b110010010000010101011 /
1"
#2190000
0"
#2195000
1%
b11111111101001011111111011000000 1
b1001111 0
b110010010000010101100 /
b10 .
1"
#2200000
0"
#2205000
b0 ,
b0 +
1"
#2210000
0"
#2215000
b0 .
1"
#2220000
0"
#2225000
0%
b1 ,
b0 1
b11111111111100001011110111000000 0
b0 /
1"
#2230000
0"
#2235000
b1 .
1"
#2240000
0"
#2245000
b11111111110100110000000000000000 1
b11110100001001000000 /
b1 +
1"
#2250000
0"
#2255000
b10 +
b11111111101110000110111101000000 1
b11111111111110000101111011100000 0
b101101110001101100000 /
1"
#2260000
0"
#2265000
b11111111101010100110011000000000 1
b11111111111111100001011110111000 0
b110001100101110101000 /
b11 +
1"
#2270000
0"
#2275000
1%
b100 +
b11111111101000110100011000000000 1
b10011000100101101 0
b110010000100010110001 /
1"
#2280000
0"
#2285000
0%
b11111111101001101101100110000000 1
b11111111111111111010000010100010 0
b110010001101111000011 /
b101 +
1"
#2290000
0"
#2295000
1%
b110 +
b11111111101001010000111101000000 1
b110100110000000 0
b110010001111010111110 /
1"
#2300000
0"
#2305000
b11111111101001011111010010000000 1
b10100000110 0
b110010010000001100100 /
b111 +
1"
#2310000
0"
#2315000
0%
b1000 +
b11111111101001100110011100000000 1
b11111111111111111101001011000110 0
b110010010000001101110 /
1"
#2320000
0"
#2325000
b11111111101001100010110111000000 1
b11111111111111111110101111100110 0
b110010010000010011100 /
b1001 +
1"
#2330000
0"
